ordr/__init__.py
ordr/asyncclient.py
ordr/classes.py
ordr/client.py
ordr/constant.py
ordr/respond.py
ordr.py-0.0.7.dist-info/LICENSE
ordr.py-0.0.7.dist-info/METADATA
ordr.py-0.0.7.dist-info/WHEEL
ordr.py-0.0.7.dist-info/top_level.txt
ordr.py-0.0.7.dist-info/RECORD
