Metadata-Version: 2.1
Name: ordr.py
Version: 0.0.7
Summary: A simple o!rdr API and Websocket wrapper.
Home-page: https://github.com/ItsRqtl/ordr.py
Author: Ryan
Author-email: itsrql@gmail.com
License: MIT
Classifier: Development Status :: 4 - Beta
Classifier: License :: OSI Approved :: MIT License
Classifier: Natural Language :: English
Classifier: Programming Language :: Python :: 3
License-File: LICENSE
Requires-Dist: requests
Requires-Dist: python-socketio
Requires-Dist: aiohttp
